critiplot/__init__.py
critiplot/grade.py
critiplot/jbi_case_report.py
critiplot/jbi_case_series.py
critiplot/mmat.py
critiplot/nos.py
critiplot/robis.py
critiplot-2.0.0.dist-info/licenses/LICENSE
critiplot-2.0.0.dist-info/METADATA
critiplot-2.0.0.dist-info/WHEEL
critiplot-2.0.0.dist-info/top_level.txt
critiplot-2.0.0.dist-info/RECORD
